LICENSE
README.md
setup.py
PsyMz.egg-info/PKG-INFO
PsyMz.egg-info/SOURCES.txt
PsyMz.egg-info/dependency_links.txt
PsyMz.egg-info/requires.txt
PsyMz.egg-info/top_level.txt
psymz/__init__.py